ara_tools/__init__.py
ara_tools/__main__.py
ara_tools/ara_config.py
ara_tools/artefact.py
ara_tools/artefact_creator.py
ara_tools/artefact_deleter.py
ara_tools/artefact_link_updater.py
ara_tools/artefact_lister.py
ara_tools/artefact_renamer.py
ara_tools/chat.py
ara_tools/classifier.py
ara_tools/classifier_validator.py
ara_tools/directory_navigator.py
ara_tools/file_classifier.py
ara_tools/file_lister.py
ara_tools/filename_validator.py
ara_tools/prompt_extractor.py
ara_tools/prompt_handler.py
ara_tools/run_file_lister.py
ara_tools/template_manager.py
ara_tools/vectorDB.py
ara_tools/version.py
ara_tools/templates/agile.artefacts
ara_tools/templates/template.businessgoal
ara_tools/templates/template.businessgoal_exploration.md
ara_tools/templates/template.capability
ara_tools/templates/template.capability_exploration.md
ara_tools/templates/template.epic
ara_tools/templates/template.epic_exploration.md
ara_tools/templates/template.example
ara_tools/templates/template.example_exploration.md
ara_tools/templates/template.feature
ara_tools/templates/template.feature_exploration.md
ara_tools/templates/template.issue
ara_tools/templates/template.keyfeature
ara_tools/templates/template.keyfeature_exploration.md
ara_tools/templates/template.steps_exploration.md
ara_tools/templates/template.task
ara_tools/templates/template.task_exploration.md
ara_tools/templates/template.userstory
ara_tools/templates/template.userstory_exploration.md
ara_tools/templates/template.vision
ara_tools/templates/template.vision_exploration.md
ara_tools/templates/prompt-creation/commands/template_businessgoal.md
ara_tools/templates/prompt-creation/commands/template_capability.md
ara_tools/templates/prompt-creation/commands/template_epic.md
ara_tools/templates/prompt-creation/commands/template_feature.md
ara_tools/templates/prompt-creation/commands/template_keyfeature.md
ara_tools/templates/prompt-creation/commands/template_task.md
ara_tools/templates/prompt-creation/commands/template_userstory.md
ara_tools-0.1.4.30.dist-info/METADATA
ara_tools-0.1.4.30.dist-info/WHEEL
ara_tools-0.1.4.30.dist-info/entry_points.txt
ara_tools-0.1.4.30.dist-info/top_level.txt
ara_tools-0.1.4.30.dist-info/RECORD
